CHANGES
LICENSE
MANIFEST.in
README.rst
setup.py
landez/__init__.py
landez/cache.py
landez/filters.py
landez/proj.py
landez/sources.py
landez/tests.py
landez/tiles.py
umilandez.egg-info/PKG-INFO
umilandez.egg-info/SOURCES.txt
umilandez.egg-info/dependency_links.txt
umilandez.egg-info/not-zip-safe
umilandez.egg-info/requires.txt
umilandez.egg-info/top_level.txt