Metadata-Version: 1.1
Name: umilandez
Version: 2.0.3.dev0
Summary: Landez is a python toolbox to manipulate map tiles.
Home-page: https://github.com/urbanmapping/landez
Author: Mathieu Leplatre
Author-email: mathieu.leplatre@makina-corpus.com
License: LPGL, see LICENSE file.
Keywords: MBTiles,Mapnik
Platform: UNKNOWN
Classifier: Programming Language :: Python :: 2.6
Classifier: Operating System :: OS Independent
Classifier: Natural Language :: English
Classifier: Topic :: Utilities
Classifier: Development Status :: 5 - Production/Stable
